 {"headers":[{"name":"User-Agent","value"     illa/5.0 (Unknown; Linux i686) Apple
WebKit/534.34 (KHTML, like Gecko) PhantomJS/1.9.8 Safa     4.34"},{"name":"Accept","value":"tex
t/html,application/xhtml+xml,application/xml;q=0.9,*/*     8"}],"id":1,"method":"GET","time":"2
014-11-24T22:09:28.458Z","url":"http://www.usenetrevol     .info/vb/attachment.php?attachmentid
=275545&d=1414778582"}
filenName Tom.Sawyer.vs.Zombies.2014.German.DL.1080p.B     .x264-GMA.par2.nzb
url http://www.usenetrevolution.info/vb/attachment.php     chmentid=275545&d=1414778582
